celery_executor/__init__.py
celery_executor/executors.py
celery_executor-0.2.0.dist-info/METADATA
celery_executor-0.2.0.dist-info/RECORD
celery_executor-0.2.0.dist-info/WHEEL
celery_executor-0.2.0.dist-info/top_level.txt
celery_executor-0.2.0.dist-info/zip-safe
