Metadata-Version: 2.1
Name: celery-executor
Version: 0.2.0
Summary: A concurrent.futures.Executor implementation using Celery as backend
Home-page: https://github.com/getninjas/celery-executor
Author: Alan Justino da Silva
Author-email: alan.justino@yahoo.com.br
License: Apache Software License 2.0
Keywords: celery_executor
Platform: UNKNOWN
Classifier: Development Status :: 2 - Pre-Alpha
Classifier: Intended Audience :: Developers
Classifier: License :: OSI Approved :: Apache Software License
Classifier: Natural Language :: English
Classifier: Programming Language :: Python :: 3
Classifier: Programming Language :: Python :: 3.5
Classifier: Programming Language :: Python :: 3.6
Requires-Dist: future (>=0.16.0)
Requires-Dist: celery
Requires-Dist: futures; python_version <= "2.7"
